odoo/addons/sale_order_carrier_auto_assign/README.rst
odoo/addons/sale_order_carrier_auto_assign/__init__.py
odoo/addons/sale_order_carrier_auto_assign/__manifest__.py
odoo/addons/sale_order_carrier_auto_assign/i18n/sale_order_carrier_auto_assign.pot
odoo/addons/sale_order_carrier_auto_assign/models/__init__.py
odoo/addons/sale_order_carrier_auto_assign/models/sale_order.py
odoo/addons/sale_order_carrier_auto_assign/readme/CONTRIBUTORS.rst
odoo/addons/sale_order_carrier_auto_assign/readme/DESCRIPTION.rst
odoo/addons/sale_order_carrier_auto_assign/static/description/icon.png
odoo/addons/sale_order_carrier_auto_assign/static/description/index.html
odoo/addons/sale_order_carrier_auto_assign/tests/__init__.py
odoo/addons/sale_order_carrier_auto_assign/tests/test_sale_order_carrier_auto_assign.py
odoo13_addon_sale_order_carrier_auto_assign-13.0.1.1.0.dist-info/METADATA
odoo13_addon_sale_order_carrier_auto_assign-13.0.1.1.0.dist-info/WHEEL
odoo13_addon_sale_order_carrier_auto_assign-13.0.1.1.0.dist-info/top_level.txt
odoo13_addon_sale_order_carrier_auto_assign-13.0.1.1.0.dist-info/RECORD
